cubepy/__init__.py
cubepy/_version.py
cubepy/converged.py
cubepy/gauss_kronrod.py
cubepy/genz_malik.py
cubepy/input.py
cubepy/integration.py
cubepy/points.py
cubepy/region.py
cubepy/type_aliases.py
cubepy-1.9.1.dist-info/LICENSE
cubepy-1.9.1.dist-info/METADATA
cubepy-1.9.1.dist-info/WHEEL
cubepy-1.9.1.dist-info/top_level.txt
cubepy-1.9.1.dist-info/zip-safe
cubepy-1.9.1.dist-info/RECORD
