Metadata-Version: 2.1
Name: cubepy
Version: 1.9.1
Summary: Adaptive Multiple Integration in Python
Author: Alex Reustle
Author-email: areustledev@gmail.com
License: MIT
Keywords: Integration,Numerical Analysis,Cubature,Quadrature
Classifier: Intended Audience :: Science/Research
Classifier: License :: OSI Approved :: MIT License
Classifier: Programming Language :: Python :: 3
Classifier: Programming Language :: Python :: 3 :: Only
Classifier: Topic :: Scientific/Engineering :: Mathematics
Requires-Python: >=3.7
License-File: LICENSE
Requires-Dist: numpy (>=1.21)
